partnr/__init__.py
partnr-0.0.0.dist-info/LICENSE
partnr-0.0.0.dist-info/WHEEL
partnr-0.0.0.dist-info/METADATA
partnr-0.0.0.dist-info/RECORD
